{
  "name": "GPL_SparkNotebookExecution_Primary_Azure",
  "properties": {
    "activities": [
      {
        "dependsOn": [
          {
            "activity": "Set variable1",
            "dependencyConditions": [
              "Succeeded"
            ]
          }
        ],
        "name": "If Condition1",
        "type": "IfCondition",
        "typeProperties": {
          "expression": {
            "type": "Expression",
            "value": "@equals(json(string(pipeline().parameters.TaskObject)).TMOptionals.UseNotebookActivity,'Disabled')"
          },
          "ifFalseActivities": [
            {
              "dependsOn": [],
              "name": "Execute Pipeline2",
              "type": "ExecutePipeline",
              "typeProperties": {
                "parameters": {
                  "TaskObject": {
                    "type": "Expression",
                    "value": "@pipeline().parameters.TaskObject"
                  }
                },
                "pipeline": {
                  "referenceName": "GPL_SparkNotebookExecution_NotebookActivity_Azure",
                  "type": "PipelineReference"
                },
                "waitOnCompletion": true
              },
              "userProperties": []
            }
          ],
          "ifTrueActivities": [
            {
              "dependsOn": [],
              "name": "Execute Pipeline1",
              "type": "ExecutePipeline",
              "typeProperties": {
                "parameters": {
                  "TaskObject": {
                    "type": "Expression",
                    "value": "@pipeline().parameters.TaskObject"
                  }
                },
                "pipeline": {
                  "referenceName": "GPL_SparkNotebookExecution_FunctionActivity_Azure",
                  "type": "PipelineReference"
                },
                "waitOnCompletion": true
              },
              "userProperties": []
            }
          ]
        },
        "userProperties": []
      },
      {
        "dependsOn": [],
        "name": "Set variable1",
        "type": "SetVariable",
        "typeProperties": {
          "value": {
            "type": "Expression",
            "value": "@string(pipeline().parameters.TaskObject)"
          },
          "variableName": "UseNotebookActivity"
        },
        "userProperties": []
      }
    ],
    "annotations": [],
    "folder": {
      "name": "ADS Go Fast/Data Movement/ExecuteNotebook/Azure/"
    },
    "lastPublishTime": "2022-04-06T03:50:37Z",
    "parameters": {
      "TaskObject": {
        "type": "object"
      }
    },
    "variables": {
      "NotebookExecutionComplete": {
        "defaultValue": false,
        "type": "Boolean"
      },
      "OutputMetaData": {
        "type": "String"
      },
      "SessionAllocationComplete": {
        "defaultValue": false,
        "type": "Boolean"
      },
      "UseNotebookActivity": {
        "type": "String"
      }
    }
  },
  "type": "Microsoft.Synapse/workspaces/pipelines"
}
